urest/__init__.py
urest/api/__init__.py
urest/api/base.py
urest/examples/__init__.py
urest/examples/echo.py
urest/examples/echo_server.py
urest/examples/led_control.py
urest/examples/pwmled.py
urest/examples/simpleled.py
urest/http/__init__.py
urest/http/response.py
urest/http/server.py
urest/utils/__init__.py
urest/utils/network_connect.py
urest_mp-0.2.9.dist-info/LICENCE
urest_mp-0.2.9.dist-info/METADATA
urest_mp-0.2.9.dist-info/WHEEL
urest_mp-0.2.9.dist-info/top_level.txt
urest_mp-0.2.9.dist-info/RECORD
