Metadata-Version: 2.1
Name: urest-mp
Version: 0.2.9
Summary: An embedded HTTP server, focused on very small REST-style API's
Author-email: David Love <david.love@leedsbeckett.ac.uk>
Project-URL: Homepage, https://github.com/dlove24/urest
Project-URL: Documentation, https://dlove24.github.io/urest/urest/index.html
Classifier: Programming Language :: Python :: 3
Classifier: License :: OSI Approved :: MIT License
Classifier: Operating System :: OS Independent
Requires-Python: >=3.4
License-File: LICENCE
